{
	"format_version": "1.21.0",
	"minecraft:geometry": [
		{
			"description": {
				"identifier": "geometry.goe_tnt.confirm_structure",
				"texture_width": 64,
				"texture_height": 64,
				"visible_bounds_width": 11,
				"visible_bounds_height": 6,
				"visible_bounds_offset": [0, 2, 0]
			},
			"bones": [
				{
					"name": "root",
					"pivot": [0, -1, 12]
				},
				{
					"name": "metal_frame",
					"parent": "root",
					"pivot": [0, 45.60502, 11.86292],
					"rotation": [90, 0, 0],
					"cubes": [
						{
							"origin": [7.3502, 41.72793, 8.2478],
							"size": [7, 7, 22],
							"inflate": 0.01,
							"pivot": [5.3502, 39.66575, 3.75785],
							"rotation": [-180, 0, -180],
							"uv": {
								"north": {"uv": [12, 16], "uv_size": [2, 2]},
								"east": {"uv": [4, 16], "uv_size": [4, 9.5], "uv_rotation": 90},
								"south": {"uv": [14, 16], "uv_size": [2, 2]},
								"west": {"uv": [4, 16], "uv_size": [4, 9.5], "uv_rotation": 90},
								"up": {"uv": [4, 16], "uv_size": [4, 9.5]},
								"down": {"uv": [4, 25.5], "uv_size": [4, -9.5]}
							}
						},
						{
							"origin": [-5.6498, 40.22793, -35.7321],
							"size": [11, 14, 11],
							"inflate": 0.01,
							"pivot": [-0.1498, 45.22793, -30.2321],
							"rotation": [-90, 0, -180],
							"uv": {
								"north": {"uv": [29.5, 0.5], "uv_size": [4, 7]},
								"east": {"uv": [33.5, 0.5], "uv_size": [4, 7]},
								"south": {"uv": [29.5, 0.5], "uv_size": [4, 7]},
								"west": {"uv": [33.5, 0.5], "uv_size": [4, 7]},
								"up": {"uv": [37.5, 0.5], "uv_size": [4, 4]},
								"down": {"uv": [41.5, 4.5], "uv_size": [4, -4]}
							}
						},
						{
							"origin": [-66.25, 41.47793, 8.212],
							"size": [50, 7.5, 2],
							"pivot": [-20.55, 39.16575, 4.72205],
							"rotation": [-180, 0, 180],
							"uv": {
								"north": {"uv": [0, 0], "uv_size": [50, 2]},
								"east": {"uv": [16, 16], "uv_size": [2, 2]},
								"south": {"uv": [0, 0], "uv_size": [50, 4]},
								"west": {"uv": [10, 16], "uv_size": [2, 2]},
								"up": {"uv": [50, 0], "uv_size": [-50, 2]},
								"down": {"uv": [50, 2], "uv_size": [-50, -2]}
							}
						},
						{
							"origin": [-66.25, 41.97793, -15.788],
							"size": [50, 6.6, 22],
							"pivot": [-20.55, 39.16575, 3.72205],
							"rotation": [-180, 0, 180],
							"uv": {
								"up": {"uv": [59, 40.5], "uv_size": [-50, -22]},
								"down": {"uv": [9, 18.5], "uv_size": [50, 22]}
							}
						},
						{
							"origin": [-59.25, 43.77793, -4.788],
							"size": [36, 5.5, 9],
							"pivot": [-20.55, 41.16575, 3.72205],
							"rotation": [-180, 0, 180],
							"uv": {
								"up": {"uv": [57.5, 62.5], "uv_size": [-48, -12]}
							}
						},
						{
							"origin": [-64.25, 43.77793, -14.788],
							"size": [45, 5.5, 10],
							"pivot": [-20.55, 41.16575, 3.72205],
							"rotation": [-180, 0, 180],
							"uv": {
								"up": {"uv": [51, 50.5], "uv_size": [-37, -8]}
							}
						},
						{
							"origin": [-66.25, 41.47793, -30.7478],
							"size": [50, 7.5, 2],
							"pivot": [-20.55, 39.16575, -2.75785],
							"rotation": [180, 0, 180],
							"uv": {
								"north": {"uv": [0, 0], "uv_size": [50, 4]},
								"east": {"uv": [18, 16], "uv_size": [-2, 2]},
								"south": {"uv": [0, 0], "uv_size": [50, 4]},
								"west": {"uv": [12, 16], "uv_size": [-2, 2]},
								"up": {"uv": [50, 2], "uv_size": [-50, -2]},
								"down": {"uv": [50, 0], "uv_size": [-50, 2]}
							}
						},
						{
							"origin": [13.2679, 41.47793, -12.35],
							"size": [26, 7.5, 2],
							"pivot": [14.4179, 45.22793, 0.3821],
							"rotation": [0, -90, 0],
							"uv": {
								"north": {"uv": [0, 8], "uv_size": [26, -4]},
								"east": {"uv": [18, 14], "uv_size": [-2, 4]},
								"south": {"uv": [0, 8], "uv_size": [26, -4]},
								"west": {"uv": [16, 14], "uv_size": [2, 4]},
								"up": {"uv": [26, 4], "uv_size": [-26, 2]},
								"down": {"uv": [26, 6], "uv_size": [-26, -2]}
							}
						},
						{
							"origin": [-14.7679, 41.47793, 11.6142],
							"size": [26, 7.5, 2],
							"pivot": [-13.6179, 45.22793, 0.3821],
							"rotation": [0, -90, 0],
							"uv": {
								"north": {"uv": [0, 8], "uv_size": [26, -4]},
								"east": {"uv": [16, 14], "uv_size": [2, 4]},
								"south": {"uv": [0, 8], "uv_size": [26, -4]},
								"west": {"uv": [18, 14], "uv_size": [-2, 4]},
								"up": {"uv": [26, 6], "uv_size": [-26, -2]},
								"down": {"uv": [26, 4], "uv_size": [-26, 2]}
							}
						}
					]
				}
			]
		}
	]
}