{
	"format_version": "1.12.0",
	"minecraft:geometry": [
		{
			"description": {
				"identifier": "geometry.witch_tnt",
				"texture_width": 128,
				"texture_height": 128,
				"visible_bounds_width": 3,
				"visible_bounds_height": 3.5,
				"visible_bounds_offset": [0, 1.25, 0]
			},
			"bones": [
				{
					"name": "bb_main",
					"pivot": [0, 0, 0],
					"cubes": [
						{"origin": [-6, 2, -8], "size": [16, 14, 16], "pivot": [0.2478, 14.7604, -0.2968], "rotation": [0, -90, 0], "uv": [0, 22]},
						{"origin": [-5, 0, -7], "size": [14, 8, 14], "pivot": [0.2478, 14.7604, -0.2968], "rotation": [0, -90, 0], "uv": [56, 52]},
						{
							"origin": [-1.6544, 20.94453, -15.16632],
							"size": [0, 2.6544, 2.6544],
							"pivot": [0.2478, 14.7604, -0.2968],
							"rotation": [0, -90, -15],
							"uv": {
								"west": {"uv": [50.06, 77.06], "uv_size": [5.88, 5.88]}
							}
						},
						{
							"origin": [9.3456, 20.23863, -10.33669],
							"size": [0, 2.6544, 2.6544],
							"pivot": [-0.7522, 12.7604, -0.2968],
							"rotation": [0, -90, -15],
							"uv": {
								"west": {"uv": [50.06, 77.06], "uv_size": [5.88, 5.88]}
							}
						},
						{
							"origin": [9.3456, 23.74077, 6.86051],
							"size": [0, 2.6544, 2.6544],
							"pivot": [-0.7522, 14.7604, -0.2968],
							"rotation": [0, -90, -15],
							"uv": {
								"west": {"uv": [50.06, 77.06], "uv_size": [5.88, 5.88]}
							}
						},
						{
							"origin": [-5.6544, 12.40848, 10.93226],
							"size": [0, 2.6544, 2.6544],
							"pivot": [0.2478, 14.7604, -0.2968],
							"rotation": [0, -90, -15],
							"uv": {
								"west": {"uv": [50.06, 77.06], "uv_size": [5.88, 5.88]}
							}
						},
						{
							"origin": [-10.97962, 16.11593, -12.21171],
							"size": [0, 2.6544, 2.6544],
							"pivot": [0.2478, 14.7604, 2.7032],
							"rotation": [0, -77.5, 10],
							"uv": {
								"west": {"uv": [50.06, 77.06], "uv_size": [5.88, 5.88]}
							}
						},
						{
							"origin": [-9.53367, 12.70456, 8.47041],
							"size": [0, 2.6544, 2.6544],
							"pivot": [1.2478, 13.7604, -0.2968],
							"rotation": [0, -62.5, 12.5],
							"uv": {
								"west": {"uv": [50.06, 77.06], "uv_size": [5.88, 5.88]}
							}
						},
						{
							"origin": [-4.4, 25.4, 4],
							"size": [4, 4, 0],
							"uv": {
								"south": {"uv": [4.5, 4.5], "uv_size": [3, 5]}
							}
						}
					]
				},
				{
					"name": "Hat",
					"pivot": [-2.6, 26.4, -0.3],
					"cubes": [
						{"origin": [-8, 14.98587, -9.94621], "size": [20, 2, 20], "pivot": [0.2478, 14.7604, -0.2968], "rotation": [0, -90, 2.5], "uv": [0, 0]},
						{"origin": [-5, 16.38264, -6.79791], "size": [14, 5, 14], "pivot": [0.2478, 14.7604, -0.2968], "rotation": [0, -90, 2.5], "uv": [0, 52]},
						{"origin": [-2.62099, 18.44046, -3.55597], "size": [6, 5, 6], "pivot": [0.2478, 14.7604, -0.2968], "rotation": [-76.73868, 72.32786, -82.12352], "uv": [20, 71]},
						{"origin": [-2.93617, 18.94193, -8.11666], "size": [4, 5, 2], "pivot": [0.2478, 12.7604, -0.2968], "rotation": [-55, -2.5, 0], "uv": [64, 43]}
					]
				},
				{
					"name": "potions",
					"pivot": [16, 2, -27],
					"cubes": [
						{
							"origin": [10.36238, 5.10275, 12.81905],
							"size": [0, 8.47, 5.7],
							"pivot": [0.2478, 14.7604, -0.2968],
							"rotation": [0, -75, -12.5],
							"uv": {
								"west": {"uv": [67.56, 78.06], "uv_size": [6.88, 10.88]}
							}
						},
						{
							"origin": [-11.56, 4.89041, -16.05563],
							"size": [0, 8.47, 5.7],
							"pivot": [-2.7522, 14.7604, -0.2968],
							"rotation": [0, -90, 12.5],
							"uv": {
								"west": {"uv": [75.56, 32.06], "uv_size": [6.88, 10.88]}
							}
						},
						{
							"origin": [5.99, 2.80635, -16.05394],
							"size": [0, 8.47, 5.7],
							"pivot": [-2.7522, 12.7604, -0.2968],
							"rotation": [0, -90, -7.5],
							"uv": {
								"west": {"uv": [11.56, 81.06], "uv_size": [6.88, 10.88]}
							}
						}
					]
				}
			]
		}
	]
}